{
  "symbol_true": "✅",
  "symbol_false": "❌",
  "indexFavShip": "0",
  "ships": [
    {
      "name": "Hyp Aufklärer-Klasse",
      "shipClass": "Drohne",
      "att": 0,
      "def": 0,
      "drive": "HYP",
      "drive_s": 127,
      "freight": 0,
      "lkom": false,
      "tt": false,
      "carrier": false,
      "fe": 103,
      "kr": 46,
      "fr": 59,
      "or": 101,
      "fz": 43,
      "au": 0
    },
    {
      "name": "Observerdrohnen-Klasse",
      "shipClass": "Drohne",
      "att": 0,
      "def": 0,
      "drive": "IOB",
      "drive_s": 100,
      "freight": 0,
      "lkom": false,
      "tt": false,
      "carrier": false,
      "fe": 96,
      "kr": 267,
      "fr": 456,
      "or": 0,
      "fz": 64,
      "au": 0
    },
    {
      "name": "WhatsZAP",
      "shipClass": "Taktisch",
      "att": 1872,
      "def": 0,
      "drive": "HYP",
      "drive_s": 116,
      "freight": 0,
      "lkom": true,
      "tt": false,
      "carrier": false,
      "fe": 830,
      "kr": 1512,
      "fr": 1470,
      "or": 5052,
      "fz": 2388,
      "au": 120
    },
    {
      "name": "Shadowdestroyer II",
      "shipClass": "Leicht",
      "att": 244,
      "def": 98,
      "drive": "ION",
      "drive_s": 118,
      "freight": 0,
      "lkom": false,
      "tt": false,
      "carrier": false,
      "fe": 1088,
      "kr": 796,
      "fr": 96,
      "or": 560,
      "fz": 528,
      "au": 0
    },
    {
      "name": "Shadowdestroyer",
      "shipClass": "Leicht",
      "att": 244,
      "def": 98,
      "drive": "NUK",
      "drive_s": 134,
      "freight": 0,
      "lkom": false,
      "tt": false,
      "carrier": false,
      "fe": 1076,
      "kr": 832,
      "fr": 0,
      "or": 812,
      "fz": 468,
      "au": 0
    },
    {
      "name": "Nuk-Kolo",
      "shipClass": "Mittel",
      "att": 0,
      "def": 0,
      "drive": "NUK",
      "drive_s": 143,
      "freight": 14350,
      "lkom": false,
      "tt": false,
      "carrier": false,
      "fe": 14168,
      "kr": 9696,
      "fr": 7200,
      "or": 6776,
      "fz": 6104,
      "au": 0
    },
    {
      "name": "Hyp-Kolo",
      "shipClass": "Mittel",
      "att": 0,
      "def": 0,
      "drive": "HYP",
      "drive_s": 119,
      "freight": 14350,
      "lkom": false,
      "tt": false,
      "carrier": false,
      "fe": 15344,
      "kr": 11376,
      "fr": 9216,
      "or": 11480,
      "fz": 8120,
      "au": 0
    },
    {
      "name": "ZAPfhahn II",
      "shipClass": "Mittel",
      "att": 156,
      "def": 112,
      "drive": "NUK",
      "drive_s": 160,
      "freight": 24600,
      "lkom": true,
      "tt": false,
      "carrier": false,
      "fe": 12928,
      "kr": 2276,
      "fr": 3400,
      "or": 1176,
      "fz": 504,
      "au": 120
    },
    {
      "name": "ZAPfhahn",
      "shipClass": "Mittel",
      "att": 156,
      "def": 142,
      "drive": "HYP",
      "drive_s": 160,
      "freight": 24600,
      "lkom": true,
      "tt": false,
      "carrier": false,
      "fe": 14104,
      "kr": 3956,
      "fr": 5416,
      "or": 5880,
      "fz": 2520,
      "au": 120
    },
    {
      "name": "ZAPfsäule II",
      "shipClass": "Mittel",
      "att": 372,
      "def": 640,
      "drive": "NUK",
      "drive_s": 140,
      "freight": 49200,
      "lkom": true,
      "tt": false,
      "carrier": false,
      "fe": 24568,
      "kr": 7416,
      "fr": 6280,
      "or": 1736,
      "fz": 864,
      "au": 120
    },
    {
      "name": "ZAPfsäule",
      "shipClass": "Mittel",
      "att": 372,
      "def": 640,
      "drive": "HYP",
      "drive_s": 116,
      "freight": 49200,
      "lkom": true,
      "tt": false,
      "carrier": false,
      "fe": 25744,
      "kr": 9096,
      "fr": 8296,
      "or": 6440,
      "fz": 2880,
      "au": 120
    },
    {
      "name": "ZAPpelphillipp II",
      "shipClass": "Mittel",
      "att": 1959,
      "def": 808,
      "drive": "NUK",
      "drive_s": 150,
      "freight": 0,
      "lkom": true,
      "tt": false,
      "carrier": false,
      "fe": 6088,
      "kr": 9216,
      "fr": 520,
      "or": 4776,
      "fz": 2504,
      "au": 120
    },
    {
      "name": "ZAPpelphillipp",
      "shipClass": "Mittel",
      "att": 1959,
      "def": 808,
      "drive": "HYP",
      "drive_s": 126,
      "freight": 0,
      "lkom": true,
      "tt": false,
      "carrier": false,
      "fe": 7264,
      "kr": 10896,
      "fr": 2536,
      "or": 9480,
      "fz": 4520,
      "au": 120
    },
    {
      "name": "Kartoffelkanone",
      "shipClass": "Mittel",
      "att": 1959,
      "def": 1144,
      "drive": "NUK",
      "drive_s": 149,
      "freight": 0,
      "lkom": false,
      "tt": false,
      "carrier": false,
      "fe": 7768,
      "kr": 12896,
      "fr": 0,
      "or": 4776,
      "fz": 2504,
      "au": 0
    },
    {
      "name": "TheDoctor",
      "shipClass": "Schwer",
      "att": 156,
      "def": 5960,
      "drive": "NUK",
      "drive_s": 159,
      "freight": 205000,
      "lkom": true,
      "tt": false,
      "carrier": false,
      "fe": 72560,
      "kr": 70460,
      "fr": 520,
      "or": 5880,
      "fz": 2520,
      "au": 120
    },
    {
      "name": "ZAPfanlange",
      "shipClass": "Schwer",
      "att": 575,
      "def": 640,
      "drive": "NUK",
      "drive_s": 160,
      "freight": 205000,
      "lkom": true,
      "tt": false,
      "carrier": false,
      "fe": 53840,
      "kr": 23640,
      "fr": 520,
      "or": 5880,
      "fz": 2520,
      "au": 120
    },
    {
      "name": "GewürZAPfeI",
      "shipClass": "Schwer",
      "att": 575,
      "def": 640,
      "drive": "HYP",
      "drive_s": 140,
      "freight": 205000,
      "lkom": true,
      "tt": false,
      "carrier": false,
      "fe": 59720,
      "kr": 32040,
      "fr": 10600,
      "or": 29400,
      "fz": 12600,
      "au": 120
    },
    {
      "name": "Respfändund",
      "shipClass": "Schwer",
      "att": 575,
      "def": 640,
      "drive": "HYP",
      "drive_s": 118,
      "freight": 410000,
      "lkom": true,
      "tt": false,
      "carrier": false,
      "fe": 99720,
      "kr": 44040,
      "fr": 10600,
      "or": 29400,
      "fz": 12600,
      "au": 120
    },
    {
      "name": "ZAPpenduster",
      "shipClass": "Schwer",
      "att": 608,
      "def": 752,
      "drive": "NUK",
      "drive_s": 154,
      "freight": 98400,
      "lkom": false,
      "tt": true,
      "carrier": false,
      "fe": 58840,
      "kr": 10880,
      "fr": 25520,
      "or": 7000,
      "fz": 3240,
      "au": 3920
    },
    {
      "name": "GewürZAPfel",
      "shipClass": "Schwer",
      "att": 2637,
      "def": 3804,
      "drive": "HYP",
      "drive_s": 136,
      "freight": 205000,
      "lkom": true,
      "tt": false,
      "carrier": false,
      "fe": 73520,
      "kr": 68600,
      "fr": 10600,
      "or": 29400,
      "fz": 12600,
      "au": 120
    },
    {
      "name": "Stealth Gaudin",
      "shipClass": "Schwer",
      "att": 3782,
      "def": 1648,
      "drive": "NUK",
      "drive_s": 157,
      "freight": 820,
      "lkom": false,
      "tt": true,
      "carrier": false,
      "fe": 25080,
      "kr": 21680,
      "fr": 14096,
      "or": 13080,
      "fz": 6520,
      "au": 3920
    },
    {
      "name": "Gaudin II",
      "shipClass": "Schwer",
      "att": 8136,
      "def": 6464,
      "drive": "NUK",
      "drive_s": 152,
      "freight": 205,
      "lkom": true,
      "tt": false,
      "carrier": false,
      "fe": 34920,
      "kr": 64200,
      "fr": 544,
      "or": 21960,
      "fz": 11600,
      "au": 120
    },
    {
      "name": "Ulk0r II",
      "shipClass": "Schwer",
      "att": 8136,
      "def": 6464,
      "drive": "HYP",
      "drive_s": 128,
      "freight": 205,
      "lkom": true,
      "tt": false,
      "carrier": false,
      "fe": 40800,
      "kr": 72600,
      "fr": 10624,
      "or": 45480,
      "fz": 21680,
      "au": 120
    },
    {
      "name": "Gaudiin",
      "shipClass": "Schwer",
      "att": 9251,
      "def": 6072,
      "drive": "NUK",
      "drive_s": 150,
      "freight": 205,
      "lkom": true,
      "tt": false,
      "carrier": false,
      "fe": 33000,
      "kr": 59400,
      "fr": 544,
      "or": 23880,
      "fz": 12520,
      "au": 120
    },
    {
      "name": "Gaudin",
      "shipClass": "Schwer",
      "att": 11074,
      "def": 5456,
      "drive": "NUK",
      "drive_s": 145,
      "freight": 205,
      "lkom": true,
      "tt": false,
      "carrier": false,
      "fe": 30120,
      "kr": 52200,
      "fr": 544,
      "or": 27480,
      "fz": 14520,
      "au": 120
    },
    {
      "name": "Ulk0r",
      "shipClass": "Schwer",
      "att": 11074,
      "def": 5456,
      "drive": "HYP",
      "drive_s": 121,
      "freight": 205,
      "lkom": true,
      "tt": false,
      "carrier": false,
      "fe": 36000,
      "kr": 60600,
      "fr": 10624,
      "or": 51000,
      "fz": 24600,
      "au": 120
    },
    {
      "name": "IronTerror",
      "shipClass": "Schwer",
      "att": 11782,
      "def": 5456,
      "drive": "HYP",
      "drive_s": 117,
      "freight": 205,
      "lkom": true,
      "tt": false,
      "carrier": false,
      "fe": 36000,
      "kr": 60600,
      "fr": 10624,
      "or": 52680,
      "fz": 25680,
      "au": 120
    },
    {
      "name": "",
      "shipClass": "",
      "att": null,
      "def": null,
      "drive": "",
      "drive_s": null,
      "freight": null,
      "lkom": null,
      "tt": null,
      "carrier": null,
      "fe": null,
      "kr": null,
      "fr": null,
      "or": null,
      "fz": null,
      "au": null
    }
  ]
}
